[
    {
        "Position": [
            -17.68000030517578,
            9.720000267028809,
            18.709999084472656
        ],
        "Velocity": [
            0.10000000149011612,
            0.0,
            0.0
        ]
    },
    {
        "Position": [
            -17.299999237060547,
            10.649999618530273,
            18.59000015258789
        ],
        "Velocity": [
            0.10000000149011612,
            0.0,
            0.0
        ]
    },
    {
        "Position": [
            -16.959999084472656,
            2.890000104904175,
            17.969999313354492
        ],
        "Velocity": [
            0.09000000357627869,
            0.0,
            0.0
        ]
    },
    {
        "Position": [
            3.759999990463257,
            2.4600000381469727,
            34.970001220703125
        ],
        "Velocity": [
            -0.07999999821186066,
            0.0,
            0.0
        ]
    },
    {
        "Position": [
            25.8700008392334,
            7.289999961853027,
            42.31999969482422
        ],
        "Velocity": [
            -0.11999999731779099,
            0.0,
            0.0
        ]
    },
    {
        "Position": [
            30.190000534057617,
            8.5,
            31.459999084472656
        ],
        "Velocity": [
            0.0,
            0.0,
            0.05000000074505806
        ]
    },
    {
        "Position": [
            45.79999923706055,
            5.010000228881836,
            -9.930000305175781
        ],
        "Velocity": [
            -0.07999999821186066,
            0.0,
            -0.09000000357627869
        ]
    },
    {
        "Position": [
            44.90999984741211,
            6.190000057220459,
            -8.460000038146973
        ],
        "Velocity": [
            -0.05999999865889549,
            0.0,
            -0.10000000149011612
        ]
    },
    {
        "Position": [
            66.91000366210938,
            3.9800000190734863,
            -13.390000343322754
        ],
        "Velocity": [
            0.0,
            0.0,
            -0.03999999910593033
        ]
    },
    {
        "Position": [
            79.61000061035156,
            3.75,
            -15.199999809265137
        ],
        "Velocity": [
            0.0,
            0.0,
            0.09000000357627869
        ]
    },
    {
        "Position": [
            82.61000061035156,
            5.809999942779541,
            -7.190000057220459
        ],
        "Velocity": [
            0.0,
            0.0,
            -0.029999999329447746
        ]
    },
    {
        "Position": [
            87.66000366210938,
            8.100000381469727,
            -33.099998474121094
        ],
        "Velocity": [
            -0.029999999329447746,
            0.0,
            0.09000000357627869
        ]
    },
    {
        "Position": [
            86.54000091552734,
            8.729999542236328,
            -32.959999084472656
        ],
        "Velocity": [
            0.0,
            0.0,
            0.09000000357627869
        ]
    },
    {
        "Position": [
            81.5,
            11.949999809265137,
            -19.5
        ],
        "Velocity": [
            -0.09000000357627869,
            0.0,
            0.0
        ]
    },
    {
        "Position": [
            81.88999938964844,
            15.149999618530273,
            -21.030000686645508
        ],
        "Velocity": [
            0.0,
            0.0,
            -0.07000000029802322
        ]
    },
    {
        "Position": [
            80.91999816894531,
            15.1899995803833,
            -25.489999771118164
        ],
        "Velocity": [
            0.0,
            0.0,
            0.07999999821186066
        ]
    },
    {
        "Position": [
            81.6500015258789,
            15.539999961853027,
            -12.010000228881836
        ],
        "Velocity": [
            0.07999999821186066,
            0.0,
            0.0
        ]
    },
    {
        "Position": [
            71.37000274658203,
            16.68000030517578,
            -14.220000267028809
        ],
        "Velocity": [
            0.0,
            -0.07000000029802322,
            0.0
        ]
    },
    {
        "Position": [
            92.44999694824219,
            9.6899995803833,
            -29.219999313354492
        ],
        "Velocity": [
            -0.019999999552965164,
            0.029999999329447746,
            0.0
        ]
    },
    {
        "Position": [
            94.3499984741211,
            9.130000114440918,
            -24.3799991607666
        ],
        "Velocity": [
            -0.019999999552965164,
            0.03999999910593033,
            0.0
        ]
    },
    {
        "Position": [
            98.30000305175781,
            8.329999923706055,
            -29.18000030517578
        ],
        "Velocity": [
            -0.019999999552965164,
            0.029999999329447746,
            0.0
        ]
    },
    {
        "Position": [
            101.44999694824219,
            7.320000171661377,
            -28.860000610351563
        ],
        "Velocity": [
            0.0,
            0.029999999329447746,
            0.019999999552965164
        ]
    },
    {
        "Position": [
            112.22000122070313,
            1.7400000095367432,
            -16.059999465942383
        ],
        "Velocity": [
            0.0,
            0.029999999329447746,
            -0.019999999552965164
        ]
    },
    {
        "Position": [
            139.39999389648438,
            7.070000171661377,
            -44.08000183105469
        ],
        "Velocity": [
            0.0,
            0.0,
            0.0
        ]
    },
    {
        "Position": [
            125.16999816894531,
            10.65999984741211,
            -44.43000030517578
        ],
        "Velocity": [
            0.0,
            0.0,
            -0.03999999910593033
        ]
    },
    {
        "Position": [
            117.4000015258789,
            -5.710000038146973,
            35.2400016784668
        ],
        "Velocity": [
            0.0,
            0.0,
            0.0
        ]
    },
    {
        "Position": [
            116.55000305175781,
            0.9800000190734863,
            47.779998779296875
        ],
        "Velocity": [
            0.0,
            -0.07000000029802322,
            0.0
        ]
    },
    {
        "Position": [
            111.0,
            0.10000000149011612,
            48.209999084472656
        ],
        "Velocity": [
            0.0,
            -0.05999999865889549,
            0.0
        ]
    },
    {
        "Position": [
            115.0199966430664,
            0.5199999809265137,
            50.09000015258789
        ],
        "Velocity": [
            0.0,
            -0.05999999865889549,
            0.0
        ]
    },
    {
        "Position": [
            117.12000274658203,
            0.8799999952316284,
            59.47999954223633
        ],
        "Velocity": [
            0.0,
            -0.05999999865889549,
            0.0
        ]
    },
    {
        "Position": [
            112.5,
            0.6800000071525574,
            63.31999969482422
        ],
        "Velocity": [
            0.0,
            -0.07000000029802322,
            0.0
        ]
    },
    {
        "Position": [
            115.97000122070313,
            0.9100000262260437,
            63.2400016784668
        ],
        "Velocity": [
            0.0,
            -0.07999999821186066,
            0.0
        ]
    },
    {
        "Position": [
            104.08999633789063,
            0.05000000074505806,
            78.87999725341797
        ],
        "Velocity": [
            0.0,
            -0.05999999865889549,
            0.0
        ]
    },
    {
        "Position": [
            94.37999725341797,
            -4.0,
            97.56999969482422
        ],
        "Velocity": [
            -0.09000000357627869,
            0.0,
            0.0
        ]
    },
    {
        "Position": [
            80.51000213623047,
            0.17000000178813934,
            72.3499984741211
        ],
        "Velocity": [
            0.0,
            0.0,
            -0.05999999865889549
        ]
    },
    {
        "Position": [
            76.43000030517578,
            1.5700000524520874,
            68.5999984741211
        ],
        "Velocity": [
            0.07999999821186066,
            0.0,
            0.0
        ]
    },
    {
        "Position": [
            76.61000061035156,
            3.9000000953674316,
            90.66999816894531
        ],
        "Velocity": [
            -0.07999999821186066,
            0.0,
            0.0
        ]
    },
    {
        "Position": [
            90.4800033569336,
            6.980000019073486,
            55.5099983215332
        ],
        "Velocity": [
            0.0,
            0.07000000029802322,
            0.05999999865889549
        ]
    },
    {
        "Position": [
            91.33000183105469,
            7.320000171661377,
            54.97999954223633
        ],
        "Velocity": [
            0.0,
            0.07000000029802322,
            0.05000000074505806
        ]
    },
    {
        "Position": [
            92.37999725341797,
            7.449999809265137,
            56.400001525878906
        ],
        "Velocity": [
            0.0,
            0.07000000029802322,
            0.029999999329447746
        ]
    },
    {
        "Position": [
            91.77999877929688,
            7.159999847412109,
            58.290000915527344
        ],
        "Velocity": [
            0.0,
            0.05999999865889549,
            0.029999999329447746
        ]
    },
    {
        "Position": [
            93.4000015258789,
            6.929999828338623,
            57.869998931884766
        ],
        "Velocity": [
            0.0,
            0.07000000029802322,
            0.029999999329447746
        ]
    },
    {
        "Position": [
            102.93000030517578,
            8.0,
            70.27999877929688
        ],
        "Velocity": [
            -0.029999999329447746,
            0.07000000029802322,
            0.019999999552965164
        ]
    },
    {
        "Position": [
            104.66000366210938,
            8.180000305175781,
            70.22000122070313
        ],
        "Velocity": [
            -0.019999999552965164,
            0.07000000029802322,
            0.029999999329447746
        ]
    },
    {
        "Position": [
            103.91000366210938,
            8.1899995803833,
            79.05999755859375
        ],
        "Velocity": [
            -0.019999999552965164,
            0.05999999865889549,
            0.019999999552965164
        ]
    },
    {
        "Position": [
            104.2699966430664,
            8.180000305175781,
            81.12000274658203
        ],
        "Velocity": [
            -0.019999999552965164,
            0.05999999865889549,
            0.009999999776482582
        ]
    },
    {
        "Position": [
            102.77999877929688,
            8.149999618530273,
            80.8499984741211
        ],
        "Velocity": [
            -0.009999999776482582,
            0.05999999865889549,
            0.019999999552965164
        ]
    },
    {
        "Position": [
            95.54000091552734,
            8.470000267028809,
            88.41999816894531
        ],
        "Velocity": [
            0.0,
            0.05999999865889549,
            0.0
        ]
    },
    {
        "Position": [
            76.61000061035156,
            15.399999618530273,
            76.30999755859375
        ],
        "Velocity": [
            0.07000000029802322,
            0.0,
            0.0
        ]
    },
    {
        "Position": [
            76.62999725341797,
            -4.300000190734863,
            28.649999618530273
        ],
        "Velocity": [
            0.0,
            0.0,
            0.0
        ]
    },
    {
        "Position": [
            91.06999969482422,
            -4.260000228881836,
            0.12999999523162842
        ],
        "Velocity": [
            0.0,
            0.0,
            -0.07999999821186066
        ]
    },
    {
        "Position": [
            78.12000274658203,
            -3.049999952316284,
            -13.489999771118164
        ],
        "Velocity": [
            -0.05999999865889549,
            0.0,
            0.0
        ]
    },
    {
        "Position": [
            29.450000762939453,
            20.6299991607666,
            -50.9900016784668
        ],
        "Velocity": [
            0.0,
            0.0,
            0.0
        ]
    }
]